openopc2/__init__.py
openopc2/__main__.py
openopc2/cli.py
openopc2/config.py
openopc2/da_client.py
openopc2/da_com.py
openopc2/exceptions.py
openopc2/gateway_proxy.py
openopc2/gateway_server.py
openopc2/gateway_service.py
openopc2/logger.py
openopc2/opc_types.py
openopc2/pythoncom_datatypes.py
openopc2/system_health.py
openopc2/utils.py
openopc2-0.1.18.dist-info/LICENSE.txt
openopc2-0.1.18.dist-info/METADATA
openopc2-0.1.18.dist-info/WHEEL
openopc2-0.1.18.dist-info/RECORD
