Metadata-Version: 2.1
Name: openopc2
Version: 0.1.18
Summary: OPC library with a Windows gateway enabling non-Windows clients to access OPC-DA calls.
Home-page: https://github.com/iterativ/openopc2
License: GPL-2.0-or-later
Keywords: opc,openopc,opc-da,opc classic
Author: Lorenz Padberg
Author-email: lorenz.padberg@iterativ.ch
Requires-Python: >=3.8,<3.13
Classifier: Development Status :: 4 - Beta
Classifier: Intended Audience :: Manufacturing
Classifier: License :: OSI Approved :: GNU General Public License v2 or later (GPLv2+)
Classifier: Programming Language :: Python :: 3
Classifier: Programming Language :: Python :: 3.8
Classifier: Programming Language :: Python :: 3.9
Classifier: Programming Language :: Python :: 3.10
Classifier: Programming Language :: Python :: 3.11
Classifier: Programming Language :: Python :: 3.12
Classifier: Topic :: Scientific/Engineering :: Human Machine Interfaces
Classifier: Topic :: Scientific/Engineering :: Interface Engine/Protocol Translator
Requires-Dist: WMI (>=1.5.1,<2.0.0) ; sys_platform == "win32"
Requires-Dist: pyro5 (>=5.14,<6.0)
Requires-Dist: pywin32 (==304) ; sys_platform == "win32"
Requires-Dist: rich (>=12.6.0,<13.0.0)
Requires-Dist: typer[all] (>=0.6.1,<0.7.0)
Project-URL: Repository, https://github.com/iterativ/openopc2
